vitalpython/__init__.py
vitalpython/ppg/PPGSignal.py
vitalpython/ppg/__init__.py
vitalpython/ppg/params.py
vitalpython/ppg/utils.py
vitalpython/ppg/features/FeatureExtractor.py
vitalpython/ppg/features/__init__.py
vitalpython/ppg/features/features_config.py
vitalpython/ppg/features/spectral_features.py
vitalpython/ppg/features/statistical_features.py
vitalpython/ppg/features/temporal_features.py
vitalpython/ppg/features/utils.py
vitalpython/ppg/preprocess/Preprocessor.py
vitalpython/ppg/preprocess/__init__.py
vitalpython/ppg/preprocess/concatenate.py
vitalpython/ppg/preprocess/filter_baseline.py
vitalpython/ppg/preprocess/polyfit.py
vitalpython/ppg/preprocess/segment.py
vitalpython/ppg/preprocess/similarity.py
vitalpython/ppg/preprocess/validate.py
vitalpython-0.1.0.dist-info/METADATA
vitalpython-0.1.0.dist-info/WHEEL
vitalpython-0.1.0.dist-info/licenses/LICENSE
vitalpython-0.1.0.dist-info/RECORD
