Metadata-Version: 2.1
Name: vitalpython
Version: 0.1.0
Summary: VitalPy: A Vital Signal Analysis Package
Project-URL: Homepage, https://github.com/SCAI-Lab/VitalPy
Project-URL: Bug Tracker, https://github.com/SCAI-Lab/VitalPy/issues
Author-email: Ana Cisnal <cisnal@ieee.org>, Bertram Fuchs <bfuchs@student.ethz.ch>, Diego Paez-Granados <diego.paez@hest.ethz.ch>
License-File: LICENSE
Classifier: License :: OSI Approved :: GNU General Public License v3 (GPLv3)
Classifier: Operating System :: OS Independent
Classifier: Programming Language :: Python :: 3
Requires-Python: >=3.9
